tbcal/__init__.py
tbcal/tbcalculation.py
tbcal/tbmodel.py
tbcal/tbplot.py
tbcal/tbsplice.py
tbcal-1.0.8.dist-info/licenses/LICENSE
tbcal-1.0.8.dist-info/METADATA
tbcal-1.0.8.dist-info/WHEEL
tbcal-1.0.8.dist-info/top_level.txt
tbcal-1.0.8.dist-info/RECORD
