Metadata-Version: 2.4
Name: tbcal
Version: 1.0.8
Summary: A package for tight-binding calculations
Home-page: https://github.com/Jia-Shiyin/TB_model_calculation
Author: ShiyinJia
Author-email: ShiyinJia@foxmail.com
Classifier: Programming Language :: Python :: 3
Classifier: License :: OSI Approved :: MIT License
Classifier: Operating System :: OS Independent
Requires-Python: >=3.6
License-File: LICENSE
Requires-Dist: numpy
Dynamic: author
Dynamic: author-email
Dynamic: classifier
Dynamic: home-page
Dynamic: license-file
Dynamic: requires-dist
Dynamic: requires-python
Dynamic: summary
